templates/aim.j2
templates/alter.j2
templates/assist.j2
templates/chat.j2
templates/code-summary.j2
templates/code.j2
templates/commit.j2
templates/completion.j2
templates/dev.j2
templates/docstring.j2
templates/empty.j2
templates/fix_ocr.j2
templates/free.j2
templates/html.j2
templates/improvements.j2
templates/jailbreak.j2
templates/max4.j2
templates/ml-explain.j2
templates/poet.j2
templates/prose-to-script-2-shot.j2
templates/prose2script.j2
templates/readme.j2
templates/researcher.j2
templates/script-to-prose-2-shot.j2
templates/shell.j2
templates/simulator.j2
templates/summary-2-shot.j2
templates/summary.j2
templates/violet.j2
templates/waluigi.j2
templates/whitman.j2
tttp/__init__.py
tttp/__main__.py
tttp/prompter.py
turbo_text_transformer_prompts-0.1.10.dist-info/METADATA
turbo_text_transformer_prompts-0.1.10.dist-info/WHEEL
turbo_text_transformer_prompts-0.1.10.dist-info/entry_points.txt
turbo_text_transformer_prompts-0.1.10.dist-info/RECORD
