Metadata-Version: 2.1
Name: turbo-text-transformer-prompts
Version: 0.1.10
Summary: 
Author: fergus
Author-email: fergusfettes@gmail.com
Requires-Python: >3.8
Classifier: Programming Language :: Python :: 3
Classifier: Programming Language :: Python :: 3.9
Classifier: Programming Language :: Python :: 3.10
Classifier: Programming Language :: Python :: 3.11
Requires-Dist: click (>=8.1.3,<9.0.0)
Requires-Dist: ipython (>=8.10.0,<9.0.0)
Requires-Dist: jinja2 (>=3.1.2,<4.0.0)
